pun/__init__.py
pun/dep.py
pun/main.py
CaCorrection-0.0.1.dist-info/METADATA
CaCorrection-0.0.1.dist-info/WHEEL
CaCorrection-0.0.1.dist-info/top_level.txt
CaCorrection-0.0.1.dist-info/RECORD
