Metadata-Version: 2.1
Name: CaCorrection
Version: 0.0.1
Summary: Catalan Punctuation and Capitalization Restoration Model
Home-page: UNKNOWN
Author: Mehdi Hosseini Moghadam
Author-email: <m.h.moghadam1996@gmail.com>
License: UNKNOWN
Keywords: python,Punctuation and Capitalization,Catalan Punctuation,Catalan Capitalization,Catalan Speech,Catalan,Catalan Speech To Text,Catalan ASR,Catalan Speech DataSet,NeMo Punctuation,Catalan Speech To Text,Catalan ASR,Catalan Tacotron2
Platform: UNKNOWN
Classifier: Development Status :: 1 - Planning
Classifier: Intended Audience :: Developers
Classifier: Programming Language :: Python :: 3
Classifier: Operating System :: Unix
Classifier: Operating System :: MacOS :: MacOS X
Classifier: Operating System :: Microsoft :: Windows
Requires-Dist: numpy
